numcodecs_wasm_uniform_noise/__init__.py
numcodecs_wasm_uniform_noise/__init__.pyi
numcodecs_wasm_uniform_noise/codec.wasm
numcodecs_wasm_uniform_noise/py.typed
numcodecs_wasm_uniform_noise-0.4.0.dist-info/METADATA
numcodecs_wasm_uniform_noise-0.4.0.dist-info/WHEEL
numcodecs_wasm_uniform_noise-0.4.0.dist-info/entry_points.txt
numcodecs_wasm_uniform_noise-0.4.0.dist-info/top_level.txt
numcodecs_wasm_uniform_noise-0.4.0.dist-info/RECORD
